acquisition_statute_parser/__init__.py
acquisition_statute_parser/__main__.py
acquisition_statute_parser/demarcator.py
acquisition_statute_parser/elements/__init__.py
acquisition_statute_parser/elements/enacters.py
acquisition_statute_parser/elements/lapse.py
acquisition_statute_parser/elements/publications.py
acquisition_statute_parser/elements/signers.py
acquisition_statute_parser/elements/titles.py
acquisition_statute_parser/sanitizer.py
acquisition_statute_parser/sections.py
acquisition_statute_parser/setter.py
acquisition_statute_parser/utils.py
acquisition_statute_parser-0.1.2.dist-info/WHEEL
acquisition_statute_parser-0.1.2.dist-info/METADATA
acquisition_statute_parser-0.1.2.dist-info/RECORD
